docvec_cli/__init__.py
docvec_cli/document_parser.py
docvec_cli/embedding_generator.py
docvec_cli/main.py
docvec_cli/output_formatter.py
docvec_cli/text_processor.py
docvec_cli-0.1.0.dist-info/METADATA
docvec_cli-0.1.0.dist-info/WHEEL
docvec_cli-0.1.0.dist-info/entry_points.txt
docvec_cli-0.1.0.dist-info/top_level.txt
docvec_cli-0.1.0.dist-info/RECORD
